{"nodes": [{"id": "workspace_devcontainer_on_create_sh", "label": "on-create.sh", "file_type": "code", "source_file": "/workspace/.devcontainer/on-create.sh", "source_location": "L1", "metadata": {"language": "bash", "kind": "file"}}, {"id": "workspace_devcontainer_on_create_sh__entry", "label": "on-create.sh script", "file_type": "code", "source_file": "/workspace/.devcontainer/on-create.sh", "source_location": "L1", "metadata": {"language": "bash", "kind": "bash_entrypoint"}}, {"id": "devcontainer_on_create_load_secrets_file", "label": "load_secrets_file()", "file_type": "code", "source_file": "/workspace/.devcontainer/on-create.sh", "source_location": "L17", "metadata": {"language": "bash", "kind": "bash_function"}}, {"id": "devcontainer_on_create_optional", "label": "optional()", "file_type": "code", "source_file": "/workspace/.devcontainer/on-create.sh", "source_location": "L79", "metadata": {"language": "bash", "kind": "bash_function"}}], "edges": [{"source": "workspace_devcontainer_on_create_sh", "target": "workspace_devcontainer_on_create_sh__entry", "relation": "contains", "confidence": "EXTRACTED", "source_file": "/workspace/.devcontainer/on-create.sh", "source_location": "L1", "weight": 1.0}, {"source": "workspace_devcontainer_on_create_sh", "target": "devcontainer_on_create_load_secrets_file", "relation": "defines", "confidence": "EXTRACTED", "source_file": "/workspace/.devcontainer/on-create.sh", "source_location": "L17", "weight": 1.0}, {"source": "workspace_devcontainer_on_create_sh", "target": "file", "relation": "imports", "confidence": "EXTRACTED", "source_file": "/workspace/.devcontainer/on-create.sh", "source_location": "L23", "weight": 1.0, "context": "import"}, {"source": "workspace_devcontainer_on_create_sh", "target": "workspace_devcontainer_on_create_setup_proto_sh", "relation": "imports_from", "confidence": "EXTRACTED", "source_file": "/workspace/.devcontainer/on-create.sh", "source_location": "L65", "weight": 1.0, "context": "import"}, {"source": "workspace_devcontainer_on_create_sh", "target": "devcontainer_on_create_optional", "relation": "defines", "confidence": "EXTRACTED", "source_file": "/workspace/.devcontainer/on-create.sh", "source_location": "L79", "weight": 1.0}, {"source": "workspace_devcontainer_on_create_sh", "target": "1", "relation": "imports", "confidence": "EXTRACTED", "source_file": "/workspace/.devcontainer/on-create.sh", "source_location": "L80", "weight": 1.0, "context": "import"}, {"source": "workspace_devcontainer_on_create_sh", "target": "workspace_devcontainer_on_create_setup_shell_sh", "relation": "imports_from", "confidence": "EXTRACTED", "source_file": "/workspace/.devcontainer/on-create.sh", "source_location": "L125", "weight": 1.0, "context": "import"}, {"source": "workspace_devcontainer_on_create_sh__entry", "target": "devcontainer_on_create_load_secrets_file", "relation": "calls", "confidence": "EXTRACTED", "source_file": "/workspace/.devcontainer/on-create.sh", "source_location": "L36", "weight": 1.0, "context": "call"}, {"source": "workspace_devcontainer_on_create_sh__entry", "target": "devcontainer_on_create_optional", "relation": "calls", "confidence": "EXTRACTED", "source_file": "/workspace/.devcontainer/on-create.sh", "source_location": "L84", "weight": 1.0, "context": "call"}]}